datacleanerpro/__init__.py
datacleanerpro-0.1.1.dist-info/licenses/LICENSE
datacleanerpro-0.1.1.dist-info/METADATA
datacleanerpro-0.1.1.dist-info/WHEEL
datacleanerpro-0.1.1.dist-info/top_level.txt
datacleanerpro-0.1.1.dist-info/RECORD
