Metadata-Version: 2.4
Name: datacleanerpro
Version: 0.1.1
Summary: A simple and efficient data cleaning library for CSV files
Home-page: https://github.com/yourusername/datacleanerpro
Author: Nabiya Inamdar
Author-email: Nabiya Inamdar <nabiya.inamdar@example.com>
License: MIT License
Project-URL: Homepage, https://github.com/yourusername/datacleanerpro
Project-URL: Bug Tracker, https://github.com/yourusername/datacleanerpro/issues
Project-URL: Documentation, https://github.com/yourusername/datacleanerpro#readme
Project-URL: Source Code, https://github.com/yourusername/datacleanerpro
Keywords: data cleaning,csv,pandas,data processing
Classifier: Development Status :: 3 - Alpha
Classifier: Intended Audience :: Developers
Classifier: Topic :: Software Development :: Libraries :: Python Modules
Classifier: Programming Language :: Python :: 3
Classifier: Programming Language :: Python :: 3.7
Classifier: Programming Language :: Python :: 3.8
Classifier: Programming Language :: Python :: 3.9
Classifier: Programming Language :: Python :: 3.10
Classifier: Programming Language :: Python :: 3.11
Classifier: License :: OSI Approved :: MIT License
Classifier: Operating System :: OS Independent
Requires-Python: >=3.7
License-File: LICENSE
Requires-Dist: pandas
Dynamic: author
Dynamic: home-page
Dynamic: license-file
Dynamic: requires-python
